Pwn4Sage/.DS_Store
Pwn4Sage/__init__.py
Pwn4Sage/pwn.py
Pwn4Sage-1.4.1.dist-info/LICENSE
Pwn4Sage-1.4.1.dist-info/METADATA
Pwn4Sage-1.4.1.dist-info/WHEEL
Pwn4Sage-1.4.1.dist-info/top_level.txt
Pwn4Sage-1.4.1.dist-info/RECORD
