Metadata-Version: 2.1
Name: Pwn4Sage
Version: 1.4.1
Summary: A simplified Pwntools for SageMath
Home-page: https://github.com/Harry0597/Pwn4Sage
Author: Harry0597
Author-email: 1915885792@qq.com
License: MIT
Classifier: Programming Language :: Python
Classifier: Programming Language :: Python :: 3
Classifier: Programming Language :: Python :: 3.5
Classifier: Programming Language :: Python :: 3.5
Classifier: Programming Language :: Python :: 3.6
Classifier: Programming Language :: Python :: 3.7
Classifier: Programming Language :: Python :: Implementation :: CPython
License-File: LICENSE
